gengive/__init__.py
gengive/__main__.py
gengive/cli.py
gengive/gengive.py
gengive-2023.6.19.dist-info/LICENSE
gengive-2023.6.19.dist-info/METADATA
gengive-2023.6.19.dist-info/WHEEL
gengive-2023.6.19.dist-info/entry_points.txt
gengive-2023.6.19.dist-info/top_level.txt
gengive-2023.6.19.dist-info/RECORD
